LICENSE.txt
README.md
setup.cfg
setup.py
Shyne/Assets.py
Shyne/DataHandler.py
Shyne/Game.py
Shyne/Previewer.py
Shyne/Shyne_.py
Shyne/Sprite.py
Shyne/SpritePicker.py
Shyne/SpriteSelector.py
Shyne/__init__.py
Shyne/libs_install.py
Shyne/Assets/Images/add.png
Shyne/Prefabs/Communication.py
Shyne/Prefabs/Inputs.py
Shyne/Prefabs/Looks.py
Shyne/Prefabs/Motion.py
Shyne/Prefabs/Sounds.py
Shyne/Prefabs/__init__.py
shyne.egg-info/PKG-INFO
shyne.egg-info/SOURCES.txt
shyne.egg-info/dependency_links.txt
shyne.egg-info/requires.txt
shyne.egg-info/top_level.txt